AirSpider/__init__.py
AirSpider/exceptions.py
AirSpider/field.py
AirSpider/item.py
AirSpider/middleware.py
AirSpider/request.py
AirSpider/response.py
AirSpider/spider.py
AirSpider/utils/__init__.py
AirSpider/utils/log.py
AirSpider-2.0.4.dist-info/LICENSE
AirSpider-2.0.4.dist-info/METADATA
AirSpider-2.0.4.dist-info/WHEEL
AirSpider-2.0.4.dist-info/top_level.txt
AirSpider-2.0.4.dist-info/RECORD
