Metadata-Version: 2.1
Name: AirSpider
Version: 2.0.4
Summary: An Easy-to-use and Fast Python Spider Framework
Home-page: https://pypi.org/project/airspider/
Author: Liu Xunzhuo
Author-email: mixdeers@gmail.com
License: MIT
Project-URL: Documentation, https://github.com/xunzhuo/AirSpider
Project-URL: Source, https://github.com/xunzhuo/AirSpider
Platform: UNKNOWN
Classifier: Framework :: AsyncIO
Classifier: Intended Audience :: Developers
Classifier: Development Status :: 4 - Beta
Classifier: License :: OSI Approved :: MIT License
Classifier: Operating System :: POSIX :: Linux
Classifier: Operating System :: MacOS :: MacOS X
Classifier: Operating System :: POSIX :: BSD
Classifier: Operating System :: Microsoft :: Windows
Classifier: Programming Language :: Python :: 3.6
Classifier: Programming Language :: Python :: 3.7
Classifier: Programming Language :: Python :: 3.8
Classifier: Topic :: Internet :: WWW/HTTP
Classifier: Topic :: Software Development :: Libraries :: Application Frameworks
Classifier: Topic :: Software Development :: Libraries :: Python Modules
Requires-Python: >=3.6
Requires-Dist: aiohttp (>=3.5.4)
Requires-Dist: cssselect
Requires-Dist: lxml
Provides-Extra: uvloop
Requires-Dist: uvloop ; extra == 'uvloop'
